mcp_server_weather/__init__.py
mcp_server_weather/__main__.py
mcp_server_weather/server.py
mcp_server_weather_xiawenzhuo-0.1.2.dist-info/METADATA
mcp_server_weather_xiawenzhuo-0.1.2.dist-info/WHEEL
mcp_server_weather_xiawenzhuo-0.1.2.dist-info/entry_points.txt
mcp_server_weather_xiawenzhuo-0.1.2.dist-info/top_level.txt
mcp_server_weather_xiawenzhuo-0.1.2.dist-info/RECORD
