Metadata-Version: 2.4
Name: mcp-server-weather-xiawenzhuo
Version: 0.1.2
Summary: Add your description here
Requires-Python: >=3.11
Requires-Dist: dotenv>=0.9.9
Requires-Dist: fastmcp>=2.14.1
Requires-Dist: mcp>=1.24.0
Requires-Dist: openai>=2.14.0
